odoo/addons/runbot_travis2docker/README.rst
odoo/addons/runbot_travis2docker/__init__.py
odoo/addons/runbot_travis2docker/__manifest__.py
odoo/addons/runbot_travis2docker/demo/runbot_repo_demo.xml
odoo/addons/runbot_travis2docker/models/__init__.py
odoo/addons/runbot_travis2docker/models/runbot_branch.py
odoo/addons/runbot_travis2docker/models/runbot_build.py
odoo/addons/runbot_travis2docker/models/runbot_repo.py
odoo/addons/runbot_travis2docker/static/description/icon.png
odoo/addons/runbot_travis2docker/templates/build.xml
odoo/addons/runbot_travis2docker/tests/__init__.py
odoo/addons/runbot_travis2docker/tests/test_runbot_build.py
odoo/addons/runbot_travis2docker/views/runbot_repo_view.xml
odoo11_addon_runbot_travis2docker-11.0.1.1.0.dist-info/METADATA
odoo11_addon_runbot_travis2docker-11.0.1.1.0.dist-info/WHEEL
odoo11_addon_runbot_travis2docker-11.0.1.1.0.dist-info/top_level.txt
odoo11_addon_runbot_travis2docker-11.0.1.1.0.dist-info/RECORD
