Metadata-Version: 2.1
Name: odoo11-addon-runbot-travis2docker
Version: 11.0.1.1.0
Summary: Generate docker with odoo instance based on .travis.yml
Home-page: https://github.com/OCA/runbot-addons
Author: Vauxoo,Odoo Community Association (OCA)
Author-email: support@odoo-community.org
License: AGPL-3
Platform: UNKNOWN
Classifier: Programming Language :: Python
Classifier: Framework :: Odoo
Classifier: Framework :: Odoo :: 11.0
Classifier: License :: OSI Approved :: GNU Affero General Public License v3
Requires-Python: >=2.7, !=3.0.*, !=3.1.*, !=3.2.*, !=3.3.*, !=3.4.*
Requires-Dist: odoo11-addon-runbot
Requires-Dist: odoo (<11.1dev,>=11.0a)
Requires-Dist: travis2docker
